tacconfig/__init__.py
tacconfig/config.py
tacconfig-0.5.4.data/data/VERSION
tacconfig-0.5.4.data/data/requirements.txt
tacconfig-0.5.4.dist-info/LICENSE
tacconfig-0.5.4.dist-info/METADATA
tacconfig-0.5.4.dist-info/WHEEL
tacconfig-0.5.4.dist-info/top_level.txt
tacconfig-0.5.4.dist-info/RECORD
