Metadata-Version: 2.1
Name: tacconfig
Version: 0.5.4
Summary: Hierarchical configuration package for containers, web apps, and services
Home-page: https://github.com/TACC/tacconfig
Author: Matthew W. Vaughn
Author-email: vaughn@tacc.utexas.edu
License: BSD
Platform: UNKNOWN
Classifier: Development Status :: 4 - Beta
Classifier: Intended Audience :: Developers
Classifier: License :: OSI Approved :: BSD License
Classifier: Natural Language :: English
Classifier: Programming Language :: Python
Classifier: Programming Language :: Python :: 2
Classifier: Programming Language :: Python :: 2.7
Classifier: Programming Language :: Python :: 3
Classifier: Programming Language :: Python :: 3.6
Classifier: Operating System :: OS Independent
Classifier: Environment :: Other Environment
Classifier: Topic :: Software Development :: Libraries :: Python Modules
Requires-Dist: attrdict
Requires-Dist: PyYAML
